xcube_cci/__init__.py
xcube_cci/cciodp.py
xcube_cci/chunkstore.py
xcube_cci/constants.py
xcube_cci/dataaccess.py
xcube_cci/dataframeaccess.py
xcube_cci/dtaccess.py
xcube_cci/kcaccess.py
xcube_cci/normalize.py
xcube_cci/odpconnector.py
xcube_cci/plugin.py
xcube_cci/sessionexecutor.py
xcube_cci/timerangegetter.py
xcube_cci/timeutil.py
xcube_cci/vdcaccess.py
xcube_cci/version.py
xcube_cci/zarraccess.py
xcube_cci/data/__init__.py
xcube_cci/data/dataset_states.json
xcube_cci/data/datatree_states.json
xcube_cci/data/excluded_data_sources
xcube_cci/data/geodataframe_states.json
xcube_cci/data/kc_refs.json
xcube_cci/data/stores.yml
xcube_cci/data/vectordatacube_states.json
xcube_cci/data/zarr_to_dsrids
xcube_cci-0.12.1.data/data/xcube_cci/dataset_states.json
xcube_cci-0.12.1.data/data/xcube_cci/datatree_states.json
xcube_cci-0.12.1.data/data/xcube_cci/excluded_data_sources
xcube_cci-0.12.1.data/data/xcube_cci/geodataframe_states.json
xcube_cci-0.12.1.data/data/xcube_cci/kc_refs.json
xcube_cci-0.12.1.data/data/xcube_cci/stores.yml
xcube_cci-0.12.1.data/data/xcube_cci/vectordatacube_states.json
xcube_cci-0.12.1.dist-info/licenses/LICENSE
xcube_cci-0.12.1.dist-info/METADATA
xcube_cci-0.12.1.dist-info/WHEEL
xcube_cci-0.12.1.dist-info/entry_points.txt
xcube_cci-0.12.1.dist-info/top_level.txt
xcube_cci-0.12.1.dist-info/RECORD
