Metadata-Version: 2.4
Name: xcube_cci
Version: 0.12.1
Summary: An xcube plugin that allows generating data cubes from the ESA CCI Open Data Portal.
Author: ESA CCI Toolbox Development Team
License: MIT License
Project-URL: Homepage, https://github.com/esa-cci/xcube-cci
Project-URL: Bug Tracker, https://github.com/esa-cci/xcube-cci/issues
Project-URL: Changelog, https://github.com/esa-cci/xcube-cci/CHANGES.md
Project-URL: Download, https://pypi.org/project/xcube-cci/#files
Project-URL: Release notes, https://github.com/esa-cci/xcube-cci/releases
Keywords: data science,cci,climate data
Classifier: Programming Language :: Python
Classifier: Programming Language :: Python :: 3
Classifier: Programming Language :: Python :: 3.10
Classifier: Programming Language :: Python :: 3.11
Classifier: License :: OSI Approved :: MIT License
Classifier: Operating System :: OS Independent
Requires-Python: >=3.10
License-File: LICENSE
Requires-Dist: aiohttp>=3.6
Requires-Dist: lxml>=4.5
Requires-Dist: nest-asyncio>=1.3
Requires-Dist: numpy>=2
Requires-Dist: pydap<=3.5.3,>=3.4
Requires-Dist: rioxarray
Requires-Dist: xcube-core>=1.8.0
Requires-Dist: xvec
Requires-Dist: zarr<3
Provides-Extra: dev
Requires-Dist: pytest; extra == "dev"
Requires-Dist: pytest-cov; extra == "dev"
Dynamic: license-file
